[
  {
    "name": null,
    "methods": [
      "HEAD",
      "GET"
    ],
    "paramNames": [],
    "path": "/",
    "regexp": "/^(?:\\/(?=$))?$/",
    "stack": [
      "wrappedController"
    ]
  },
  {
    "name": null,
    "methods": [
      "POST"
    ],
    "paramNames": [],
    "path": "/api/task/list",
    "regexp": "/^\\/api\\/task\\/list(?:\\/(?=$))?$/",
    "stack": [
      "wrappedController"
    ]
  },
  {
    "name": null,
    "methods": [
      "POST"
    ],
    "paramNames": [],
    "path": "/api/task/add",
    "regexp": "/^\\/api\\/task\\/add(?:\\/(?=$))?$/",
    "stack": [
      "wrappedController"
    ]
  },
  {
    "name": null,
    "methods": [
      "DELETE"
    ],
    "paramNames": [],
    "path": "/api/task/delete",
    "regexp": "/^\\/api\\/task\\/delete(?:\\/(?=$))?$/",
    "stack": [
      "wrappedController"
    ]
  },
  {
    "name": null,
    "methods": [
      "PUT"
    ],
    "paramNames": [],
    "path": "/api/task/update",
    "regexp": "/^\\/api\\/task\\/update(?:\\/(?=$))?$/",
    "stack": [
      "wrappedController"
    ]
  },
  {
    "name": null,
    "methods": [
      "PUT"
    ],
    "paramNames": [],
    "path": "/api/task/finish",
    "regexp": "/^\\/api\\/task\\/finish(?:\\/(?=$))?$/",
    "stack": [
      "wrappedController"
    ]
  },
  {
    "name": null,
    "methods": [
      "POST"
    ],
    "paramNames": [],
    "path": "/api/task/detail",
    "regexp": "/^\\/api\\/task\\/detail(?:\\/(?=$))?$/",
    "stack": [
      "wrappedController"
    ]
  },
  {
    "name": null,
    "methods": [
      "POST"
    ],
    "paramNames": [],
    "path": "/api/task/appeal",
    "regexp": "/^\\/api\\/task\\/appeal(?:\\/(?=$))?$/",
    "stack": [
      "wrappedController"
    ]
  },
  {
    "name": null,
    "methods": [
      "POST"
    ],
    "paramNames": [],
    "path": "/api/task/mine",
    "regexp": "/^\\/api\\/task\\/mine(?:\\/(?=$))?$/",
    "stack": [
      "wrappedController"
    ]
  },
  {
    "name": null,
    "methods": [
      "POST"
    ],
    "paramNames": [],
    "path": "/api/subtask/add",
    "regexp": "/^\\/api\\/subtask\\/add(?:\\/(?=$))?$/",
    "stack": [
      "wrappedController"
    ]
  },
  {
    "name": null,
    "methods": [
      "POST"
    ],
    "paramNames": [],
    "path": "/api/subtask/update",
    "regexp": "/^\\/api\\/subtask\\/update(?:\\/(?=$))?$/",
    "stack": [
      "wrappedController"
    ]
  },
  {
    "name": null,
    "methods": [
      "POST"
    ],
    "paramNames": [],
    "path": "/api/login",
    "regexp": "/^\\/api\\/login(?:\\/(?=$))?$/",
    "stack": [
      "wrappedController"
    ]
  },
  {
    "name": null,
    "methods": [
      "POST"
    ],
    "paramNames": [],
    "path": "/api/modifypwd",
    "regexp": "/^\\/api\\/modifypwd(?:\\/(?=$))?$/",
    "stack": [
      "wrappedController"
    ]
  },
  {
    "name": null,
    "methods": [
      "POST"
    ],
    "paramNames": [],
    "path": "/api/createaccount",
    "regexp": "/^\\/api\\/createaccount(?:\\/(?=$))?$/",
    "stack": [
      "wrappedController"
    ]
  },
  {
    "name": null,
    "methods": [
      "POST"
    ],
    "paramNames": [],
    "path": "/api/chart/pie",
    "regexp": "/^\\/api\\/chart\\/pie(?:\\/(?=$))?$/",
    "stack": [
      "wrappedController"
    ]
  },
  {
    "name": null,
    "methods": [
      "POST"
    ],
    "paramNames": [],
    "path": "/api/chart/sort",
    "regexp": "/^\\/api\\/chart\\/sort(?:\\/(?=$))?$/",
    "stack": [
      "wrappedController"
    ]
  },
  {
    "name": null,
    "methods": [
      "POST"
    ],
    "paramNames": [],
    "path": "/api/chart/finishprocess",
    "regexp": "/^\\/api\\/chart\\/finishprocess(?:\\/(?=$))?$/",
    "stack": [
      "wrappedController"
    ]
  }
]